rcsbsearch/__init__.py
rcsbsearch/schema.py
rcsbsearch/search.py
rcsbsearch/update_schema.py
rcsbsearch/resources/metadata_schema.json
rcsbsearch-0.2.3.dist-info/LICENSE
rcsbsearch-0.2.3.dist-info/METADATA
rcsbsearch-0.2.3.dist-info/WHEEL
rcsbsearch-0.2.3.dist-info/top_level.txt
rcsbsearch-0.2.3.dist-info/RECORD
