Metadata-Version: 2.1
Name: rcsbsearch
Version: 0.2.3
Summary: Access the RCSB Search API
Home-page: https://github.com/sbliven/rcsbsearch
Author: Spencer Bliven
Author-email: spencer.bliven@gmail.com
License: UNKNOWN
Platform: UNKNOWN
Classifier: Programming Language :: Python :: 3
Classifier: Programming Language :: Python :: 3 :: Only
Classifier: Programming Language :: Python :: 3.7
Classifier: Programming Language :: Python :: 3.8
Classifier: Development Status :: 4 - Beta
Classifier: Operating System :: OS Independent
Classifier: Intended Audience :: Science/Research
Classifier: License :: OSI Approved :: BSD License
Classifier: Topic :: Scientific/Engineering :: Bio-Informatics
Classifier: Typing :: Typed
Requires-Python: >=3.7
Requires-Dist: requests
Requires-Dist: jsonschema
Provides-Extra: docs
Requires-Dist: sphinx ; extra == 'docs'
Requires-Dist: sphinx-rtd-theme ; extra == 'docs'
Requires-Dist: myst-parser ; extra == 'docs'
Provides-Extra: progressbar
Requires-Dist: tqdm ; extra == 'progressbar'
Provides-Extra: tests
Requires-Dist: tox ; extra == 'tests'
Requires-Dist: pytest ; extra == 'tests'
Requires-Dist: black (==20.8b1) ; extra == 'tests'
Requires-Dist: flake8 ; extra == 'tests'
Requires-Dist: mypy ; extra == 'tests'
